builder/__init__.py
builder/core.py
builder/__pycache__/__init__.cpython-311.pyc
builder/__pycache__/core.cpython-311.pyc
builder/commands/__init__.py
builder/commands/help.py
builder/commands/rebuild.py
builder/commands/run.py
builder/commands/__pycache__/__init__.cpython-311.pyc
builder/commands/__pycache__/help.cpython-311.pyc
builder/commands/__pycache__/rebuild.cpython-311.pyc
builder/commands/__pycache__/run.cpython-311.pyc
builder/templates/__init__.py
builder/templates/django_template/.gitignore
builder/templates/django_template/__init__.py
builder/templates/django_template/manage.py
builder/templates/django_template/requirements.txt
builder/templates/django_template/config/__init__.py
builder/templates/django_template/config/asgi.py
builder/templates/django_template/config/settings.py
builder/templates/django_template/config/urls.py
builder/templates/django_template/config/wsgi.py
builder/templates/django_template/home/__init__.py
builder/templates/django_template/home/admin.py
builder/templates/django_template/home/apps.py
builder/templates/django_template/home/models.py
builder/templates/django_template/home/tests.py
builder/templates/django_template/home/views.py
builder/templates/django_template/home/migrations/__init__.py
builder/templates/django_template/media/avatars/what-is-california-known-for-the-golden-gate-bridge-hero.jpg
builder/templates/django_template/static/favicon.ico
builder/templates/django_template/static/css/style.css
builder/templates/django_template/static/images/ape1.jpg
builder/templates/django_template/static/images/ape2.jpg
builder/templates/django_template/static/images/avatar.svg
builder/templates/django_template/static/images/logo.svg
builder/templates/django_template/templates/404.html
builder/templates/django_template/templates/base.html
builder/templates/django_template/templates/home.html
builder/templates/django_template/templates/account/login.html
FrameBuilder-0.1.3.dist-info/LICENSE
FrameBuilder-0.1.3.dist-info/METADATA
FrameBuilder-0.1.3.dist-info/WHEEL
FrameBuilder-0.1.3.dist-info/entry_points.txt
FrameBuilder-0.1.3.dist-info/top_level.txt
FrameBuilder-0.1.3.dist-info/RECORD
